mimeparse/__init__.py
mimeparse/mimeparse.py
lapis_mimeparse-0.1.5.dist-info/LICENSE
lapis_mimeparse-0.1.5.dist-info/WHEEL
lapis_mimeparse-0.1.5.dist-info/METADATA
lapis_mimeparse-0.1.5.dist-info/RECORD
